cohere_beamlines/Petra3_P10/RSM_post_processing.py
cohere_beamlines/Petra3_P10/__init__.py
cohere_beamlines/Petra3_P10/beam_tabs.py
cohere_beamlines/Petra3_P10/beam_verifier.py
cohere_beamlines/Petra3_P10/detectors.py
cohere_beamlines/Petra3_P10/diffractometers.py
cohere_beamlines/Petra3_P10/instrument.py
cohere_beamlines/Petra3_P10/p10_scan_reader.py
cohere_beamlines/Petra3_P10/preprocessor.py
cohere_beamlines/aps_1ide/__init__.py
cohere_beamlines/aps_1ide/beam_tabs.py
cohere_beamlines/aps_1ide/beam_verifier.py
cohere_beamlines/aps_1ide/detectors.py
cohere_beamlines/aps_1ide/diffractometers.py
cohere_beamlines/aps_1ide/instrument.py
cohere_beamlines/aps_1ide/preprocessor.py
cohere_beamlines/aps_34idc/__init__.py
cohere_beamlines/aps_34idc/beam_tabs.py
cohere_beamlines/aps_34idc/beam_verifier.py
cohere_beamlines/aps_34idc/detectors.py
cohere_beamlines/aps_34idc/diffractometers.py
cohere_beamlines/aps_34idc/instrument.py
cohere_beamlines/aps_34idc/preprocessor.py
cohere_beamlines/esrf_id01/__init__.py
cohere_beamlines/esrf_id01/beam_tabs.py
cohere_beamlines/esrf_id01/beam_verifier.py
cohere_beamlines/esrf_id01/detectors.py
cohere_beamlines/esrf_id01/diffractometers.py
cohere_beamlines/esrf_id01/instrument.py
cohere_beamlines/esrf_id01/preprocessor.py
cohere_beamlines/simple/__init__.py
cohere_beamlines/simple/beam_verifier.py
cohere_beamlines/simple/detectors.py
cohere_beamlines/simple/diffractometers.py
cohere_beamlines/simple/instrument.py
cohere_beamlines/simple/preprocessor.py
cohere_beamlines-4.4.0.dist-info/licenses/LICENSE
cohere_beamlines-4.4.0.dist-info/METADATA
cohere_beamlines-4.4.0.dist-info/WHEEL
cohere_beamlines-4.4.0.dist-info/top_level.txt
cohere_beamlines-4.4.0.dist-info/RECORD
